kitsunekko_tools/__init__.py
kitsunekko_tools/__main__.py
kitsunekko_tools/__version__.py
kitsunekko_tools/common.py
kitsunekko_tools/config.py
kitsunekko_tools/consts.py
kitsunekko_tools/download.py
kitsunekko_tools/entry.py
kitsunekko_tools/file_downloader.py
kitsunekko_tools/filesystem.py
kitsunekko_tools/ignore.py
kitsunekko_tools/local_state.py
kitsunekko_tools/mega_upload.py
kitsunekko_tools/sanitize.py
kitsunekko_tools/api_access/__init__.py
kitsunekko_tools/api_access/directory_entry.py
kitsunekko_tools/api_access/download.py
kitsunekko_tools/api_access/file_entry.py
kitsunekko_tools/api_access/rate_limit.py
kitsunekko_tools/api_access/root_directory.py
kitsunekko_tools/example_catalog/ktools.toml
kitsunekko_tools/example_catalog/rebuild.sh
kitsunekko_tools/example_catalog/_site/drama.html
kitsunekko_tools/example_catalog/_site/index.html
kitsunekko_tools/example_catalog/_site/not_found.html
kitsunekko_tools/example_catalog/_site/anime_tv/ranma-1∕2-(2024)-2nd-season.html
kitsunekko_tools/example_catalog/_site/anime_tv/spy×family-season-3.html
kitsunekko_tools/example_catalog/_site/drama_movie/sensei-no-shiroi-uso.html
kitsunekko_tools/example_catalog/_site/drama_movie/zutto-dokushin-de-iru-tsumori？.html
kitsunekko_tools/example_catalog/_site/drama_tv/setsuen-chase.html
kitsunekko_tools/example_catalog/_site/drama_tv/雪煙チェイス.html
kitsunekko_tools/example_catalog/_site/resources/logo.webp
kitsunekko_tools/example_catalog/_site/resources/site.css
kitsunekko_tools/example_catalog/_site/resources/site.js
kitsunekko_tools/example_catalog/_site/unsorted/youkai-apartment-no-yuuga-na-nichijou.html
kitsunekko_tools/example_catalog/resources/logo.webp
kitsunekko_tools/example_catalog/resources/site.css
kitsunekko_tools/example_catalog/resources/site.js
kitsunekko_tools/example_catalog/subtitles/anime_tv/Ranma 1∕2 (2024) 2nd Season/.kitsuignore
kitsunekko_tools/example_catalog/subtitles/anime_tv/Ranma 1∕2 (2024) 2nd Season/.kitsuinfo.json
kitsunekko_tools-26.1.26.0.dist-info/METADATA
kitsunekko_tools-26.1.26.0.dist-info/WHEEL
kitsunekko_tools-26.1.26.0.dist-info/entry_points.txt
kitsunekko_tools-26.1.26.0.dist-info/licenses/LICENSE
kitsunekko_tools-26.1.26.0.dist-info/RECORD
