Metadata-Version: 2.4
Name: kitsunekko-tools
Version: 26.1.26.0
Summary: A set of scripts for creating a local kitsunekko mirror.
Author-email: Ren Tatsumoto <tatsu@autistici.org>
License:                     GNU AFFERO GENERAL PUBLIC LICENSE
License-File: LICENSE
Requires-Python: >=3.12
Requires-Dist: beartype>=0.10.0
Requires-Dist: fire>=0.6.0
Requires-Dist: httpx[socks]>=0.28
Requires-Dist: jinja2>=3.1.0
